setup.py
brynq_sdk_marad/__init__.py
brynq_sdk_marad/marad.py
brynq_sdk_marad.egg-info/PKG-INFO
brynq_sdk_marad.egg-info/SOURCES.txt
brynq_sdk_marad.egg-info/dependency_links.txt
brynq_sdk_marad.egg-info/not-zip-safe
brynq_sdk_marad.egg-info/requires.txt
brynq_sdk_marad.egg-info/top_level.txt